<?xml version="1.0" encoding="UTF-8"?>

<pieces>
    <artwork>
        <title>This Is America</title>
		<artist>safezone4all</artist>
		<segment>blm</segment>
		<imageurl>artfiles/37.jpg</imageurl>
		<charity>Brooklyn Bail Fund</charity>
		<shopurl>https://www.teespring.com/this-is-america-7291</shopurl>
	</artwork>
	
	<artwork>
		<title>My Color Is Not A Crime</title>
		<artist>rat.clown</artist>
		<segment>blm</segment>
		<imageurl>artfiles/38.jpg</imageurl>
		<charity>Therapy Fund for Black Women and Girls</charity>
		<shopurl>https://teespring.com/get-my-color-is-not-a-crime</shopurl>
	</artwork>
	
	<artwork>	
		<title>Worth</title>
		<artist>rat.clown</artist>
		<segment>blm</segment>
		<imageurl>artfiles/39.jpg</imageurl>
		<charity>Therapy Fund for Black Women and Girls</charity>
		<shopurl>https://teespring.com/worth-june-2020</shopurl>
	</artwork>
	
	<artwork>
		<title>Your Racism Will Never Be Patriotic</title>
		<artist>fable_cove</artist>
		<segment>police</segment>
		<imageurl>artfiles/40.jpg</imageurl>
		<charity>ACLU</charity>
		<shopurl>https://teespring.com/your-racism-will-never-be-patr</shopurl>
	</artwork>
	
	<artwork>
		<title>Eat The Rich</title>
		<artist>clownwithlemons</artist>
		<segment>money</segment>
		<imageurl>artfiles/41.jpg</imageurl>
		<charity>Pimento Relief Fund</charity>
		<shopurl>https://teespring.com/eat-the-rich-june-2020</shopurl>
	</artwork>
	
	<artwork>
		<title>DEFUND POLICE</title>
		<artist>thereisnozoolonlyart</artist>
		<segment>police</segment>
		<imageurl>artfiles/42.jpg</imageurl>
		<charity>Campaign Zero</charity>
		<shopurl>https://teespring.com/new-defund-police</shopurl>
	</artwork>
	
	<artwork>
		<title>up in (all of our) arms</title>
		<artist>thereisnozoolonlyart</artist>
		<segment>blm</segment>
		<imageurl>artfiles/43.jpg</imageurl>
		<charity>The Advancement Project</charity>
		<shopurl>https://teespring.com/up-in-all-of-our-arms</shopurl>
	</artwork>
	
	<artwork>
		<title>I WILL STAND</title>
		<artist>thereisnozoolonlyart</artist>
		<segment>blm</segment>
		<imageurl>artfiles/44.jpg</imageurl>
		<charity>NAACP Legal Defense Fund</charity>
		<shopurl>https://teespring.com/new-i-will-stand</shopurl>
	</artwork>
		
	<!--<artwork>
		<title></title>
		<artist></artist>
		<segment></segment>
		<imageurl>artfiles/</imageurl>
		<charity></charity>
		<shopurl></shopurl>
	</artwork> -->
	
</pieces>